nifigator/__init__.py
nifigator/const.py
nifigator/converters.py
nifigator/lemongraph.py
nifigator/lemonobjects.py
nifigator/multisets.py
nifigator/nafdocument.py
nifigator/nafobjects.py
nifigator/nifgraph.py
nifigator/nifobjects.py
nifigator/nifvecobjects.py
nifigator/pdfparser.py
nifigator/search.py
nifigator/utils.py
nifigator-0.2.1.dist-info/LICENSE.txt
nifigator-0.2.1.dist-info/METADATA
nifigator-0.2.1.dist-info/WHEEL
nifigator-0.2.1.dist-info/top_level.txt
nifigator-0.2.1.dist-info/RECORD
