Metadata-Version: 2.1
Name: nifigator
Version: 0.2.1
Summary: Nifigator is a pure Python package for working with NLP in RDF/NIF
Home-page: https://github.com/DeNederlandscheBank/nifigator/
Author: Willem Jan Willemse
Author-email: w.j.willemse@dnb.nl
License: MIT/X
Project-URL: Documentation, https://nifigator.readthedocs.io/en/latest/
Project-URL: Source, https://github.com/DeNederlandscheBank/nifigator/
Platform: any
Classifier: Development Status :: 4 - Beta
Classifier: Programming Language :: Python
Requires-Python: >=3.8
License-File: LICENSE.txt
Requires-Dist: importlib-metadata
Requires-Dist: python-version <3.8
Requires-Dist: Click >=7.0
Requires-Dist: rdflib >=6.2.0
Requires-Dist: lxml >=4.9.2
Requires-Dist: unidecode >=1.3.6
Requires-Dist: iribaker >=0.2
Requires-Dist: pdfminer.six >=20221105
Requires-Dist: regex >=2022.10.31
Requires-Dist: syntok >=1.4.4
Requires-Dist: pandas
Provides-Extra: testing
Requires-Dist: setuptools ; extra == 'testing'
Requires-Dist: pytest ; extra == 'testing'
Requires-Dist: pytest-cov ; extra == 'testing'
Requires-Dist: rdflib >=6.2.0 ; extra == 'testing'
Requires-Dist: lxml >=4.9.2 ; extra == 'testing'
Requires-Dist: unidecode >=1.3.6 ; extra == 'testing'
Requires-Dist: iribaker >=0.2 ; extra == 'testing'
Requires-Dist: pdfminer.six >=20221105 ; extra == 'testing'
Requires-Dist: stanza >=1.4.2 ; extra == 'testing'
Requires-Dist: syntok >=1.4.4 ; extra == 'testing'
Requires-Dist: pandas ; extra == 'testing'
